bdm_tool-0.2.dist-info/licenses/LICENSE
bdmtool/__init__.py
bdmtool/_command.py
bdmtool/files_management.py
bdm_tool-0.2.dist-info/METADATA
bdm_tool-0.2.dist-info/WHEEL
bdm_tool-0.2.dist-info/entry_points.txt
bdm_tool-0.2.dist-info/top_level.txt
bdm_tool-0.2.dist-info/RECORD
