Metadata-Version: 2.4
Name: bdm-tool
Version: 0.2
Summary: Simple lightweight dataset versioning utility based purely on the file system and symbolic links
Author-email: Andrei Khobnia <andrei.khobnia@gmail.com>
License-Expression: MIT
Keywords: version-control,data-versioning,versioning,machine-learning,ai,data,developer-tools
Classifier: Operating System :: OS Independent
Classifier: Development Status :: 4 - Beta
Classifier: Programming Language :: Python :: 3
Classifier: Programming Language :: Python :: 3.9
Classifier: Programming Language :: Python :: 3.10
Classifier: Programming Language :: Python :: 3.11
Classifier: Programming Language :: Python :: 3.12
Requires-Python: >=3.9
License-File: LICENSE
Provides-Extra: docs
Requires-Dist: sphinx; extra == "docs"
Requires-Dist: sphinx-rtd-theme; extra == "docs"
Dynamic: license-file
